aiobloom_live/__init__.py
aiobloom_live/benchmarks.py
aiobloom_live/bloom.py
aiobloom_live/test_aiobloom.py
aiobloom_live/utils.py
tests/__init__.py
tests/test1.py
tests/test2.py
aiobloom_live-0.1.0.dist-info/LICENSE
aiobloom_live-0.1.0.dist-info/METADATA
aiobloom_live-0.1.0.dist-info/WHEEL
aiobloom_live-0.1.0.dist-info/top_level.txt
aiobloom_live-0.1.0.dist-info/RECORD
